LICENSE.txt
MANIFEST.in
README.md
setup.cfg
setup.py
universions/__init__.py
universions/_exec.py
universions/_version.py
universions/cli.py
universions/error.py
universions/version.py
universions.egg-info/PKG-INFO
universions.egg-info/SOURCES.txt
universions.egg-info/dependency_links.txt
universions.egg-info/entry_points.txt
universions.egg-info/top_level.txt
universions/git/__init__.py
universions/java/__init__.py
universions/node/__init__.py
universions/npm/__init__.py
universions/pip/__init__.py
universions/python/__init__.py
universions/python/_parser.py