Metadata-Version: 2.1
Name: universions
Version: 0.5.0
Summary: Get version of other tools.
Home-page: https://github.com/fabiencelier/universions
Author: Fabien Celier
Author-email: fabien.celier@polytechnique.org
License: LICENSE.txt
Keywords: version,versions,universal
Platform: UNKNOWN
Classifier: Development Status :: 3 - Alpha
Classifier: Intended Audience :: Developers
Classifier: Programming Language :: Python :: 3.6
Classifier: Programming Language :: Python :: 3.7
Classifier: Programming Language :: Python :: 3.8
Classifier: Operating System :: OS Independent
Requires-Python: >=3.6
